{"total":254,"page":1,"per_page":50,"total_pages":6,"filters":{"gap_sizes":["Small","Medium","Big","Huge"],"outcomes":["Bounced","Faded","Kept Falling"],"sectors":["","Communication Services","Consumer Discretionary","Consumer Staples","Energy","Financials","Health Care","Industrials","Information Technology","Materials","Real Estate","Utilities"]},"events":[{"ticker":"WST","name":"West Pharmaceutical Services","sector":"Health Care","signal_date":"2026-04-23","gap_up_pct":12.24,"selloff_pct":3.32,"outcome_1d":null,"outcome_5d":null,"outcome_10d":null,"signal_strength":67,"status":"active","catalyst_type":"earnings_beat","catalyst_headline":"WST Stock Jumps on Q1 Earnings & Sales Beat, EPS View Up on HVP Growth","gap_size":"Huge","outcome_label":"Pending","summary":"On April 23, 2026, West Pharmaceutical Services jumped 12.2% because it beat earnings expectations.","has_analysis":false},{"ticker":"TPR","name":"Tapestry, Inc.","sector":"Consumer Discretionary","signal_date":"2026-04-23","gap_up_pct":1.66,"selloff_pct":2.34,"outcome_1d":null,"outcome_5d":null,"outcome_10d":null,"signal_strength":30,"status":"active","catalyst_type":"positive_news","catalyst_headline":"5 Stocks to Buy as Retail Sales Soar Amid Ongoing Geopolitical Tensions","gap_size":"Small","outcome_label":"Pending","summary":"On April 23, 2026, Tapestry, Inc. jumped 1.7% because of positive news.","has_analysis":false},{"ticker":"SNA","name":"Snap-on","sector":"Industrials","signal_date":"2026-04-23","gap_up_pct":4.84,"selloff_pct":2.53,"outcome_1d":null,"outcome_5d":null,"outcome_10d":null,"signal_strength":62,"status":"active","catalyst_type":"earnings_beat","catalyst_headline":"Snap-on Q1 Earnings & Revenues Beat Estimates, Organic Sales Rise 3.4%","gap_size":"Medium","outcome_label":"Pending","summary":"On April 23, 2026, Snap-on jumped 4.8% because it beat earnings expectations.","has_analysis":false},{"ticker":"ROP","name":"Roper Technologies","sector":"Information Technology","signal_date":"2026-04-23","gap_up_pct":4.03,"selloff_pct":5.27,"outcome_1d":null,"outcome_5d":null,"outcome_10d":null,"signal_strength":70,"status":"active","catalyst_type":"earnings_beat","catalyst_headline":"Roper Technologies climbs on earnings beat, higher outlook and expanded buybacks","gap_size":"Medium","outcome_label":"Pending","summary":"On April 23, 2026, Roper Technologies jumped 4.0% because it beat earnings expectations.","has_analysis":false},{"ticker":"POOL","name":"Pool Corporation","sector":"Consumer Discretionary","signal_date":"2026-04-23","gap_up_pct":3.38,"selloff_pct":8.18,"outcome_1d":null,"outcome_5d":null,"outcome_10d":null,"signal_strength":67,"status":"active","catalyst_type":"earnings_beat","catalyst_headline":"Pool Corp. beats Q1 estimates on solid sales growth","gap_size":"Medium","outcome_label":"Pending","summary":"On April 23, 2026, Pool Corporation jumped 3.4% because it beat earnings expectations.","has_analysis":false},{"ticker":"PKG","name":"Packaging Corporation of America","sector":"Materials","signal_date":"2026-04-23","gap_up_pct":3.75,"selloff_pct":3.46,"outcome_1d":null,"outcome_5d":null,"outcome_10d":null,"signal_strength":61,"status":"active","catalyst_type":"earnings_beat","catalyst_headline":"Packaging Corp. Q1 Earnings Beat Estimates on Pricing and Mix","gap_size":"Medium","outcome_label":"Pending","summary":"On April 23, 2026, Packaging Corporation of America jumped 3.8% because it beat earnings expectations.","has_analysis":false},{"ticker":"ON","name":"ON Semiconductor","sector":"Information Technology","signal_date":"2026-04-23","gap_up_pct":4.29,"selloff_pct":1.41,"outcome_1d":null,"outcome_5d":null,"outcome_10d":null,"signal_strength":48,"status":"active","catalyst_type":"upgrade","catalyst_headline":"B. Riley Just Upgraded On Semiconductor to Buy and Nearly Doubled Its Price Target. Is This the Chip Comeback of 2026?","gap_size":"Medium","outcome_label":"Pending","summary":"On April 23, 2026, ON Semiconductor jumped 4.3% because an analyst upgraded the stock.","has_analysis":false},{"ticker":"ODFL","name":"Old Dominion","sector":"Industrials","signal_date":"2026-04-23","gap_up_pct":1.75,"selloff_pct":1.8,"outcome_1d":null,"outcome_5d":null,"outcome_10d":null,"signal_strength":43,"status":"active","catalyst_type":"earnings_beat","catalyst_headline":"Old Dominion Freight Line (ODFL) Expected to Beat Earnings Estimates: Should You Buy?","gap_size":"Small","outcome_label":"Pending","summary":"On April 23, 2026, Old Dominion jumped 1.8% because it beat earnings expectations.","has_analysis":false},{"ticker":"NXPI","name":"NXP Semiconductors","sector":"Information Technology","signal_date":"2026-04-23","gap_up_pct":3.67,"selloff_pct":1.45,"outcome_1d":null,"outcome_5d":null,"outcome_10d":null,"signal_strength":26,"status":"active","catalyst_type":null,"catalyst_headline":null,"gap_size":"Medium","outcome_label":"Pending","summary":"On April 23, 2026, NXP Semiconductors jumped 3.7% because of big news.","has_analysis":false},{"ticker":"NDAQ","name":"Nasdaq, Inc.","sector":"Financials","signal_date":"2026-04-23","gap_up_pct":1.73,"selloff_pct":3.76,"outcome_1d":null,"outcome_5d":null,"outcome_10d":null,"signal_strength":52,"status":"active","catalyst_type":"earnings_beat","catalyst_headline":"Nasdaq Q1 Earnings & Revenues Beat Estimates, Dividend Raised","gap_size":"Small","outcome_label":"Pending","summary":"On April 23, 2026, Nasdaq, Inc. jumped 1.7% because it beat earnings expectations.","has_analysis":false},{"ticker":"MOH","name":"Molina Healthcare","sector":"Health Care","signal_date":"2026-04-23","gap_up_pct":7.69,"selloff_pct":1.78,"outcome_1d":null,"outcome_5d":null,"outcome_10d":null,"signal_strength":59,"status":"active","catalyst_type":"earnings_beat","catalyst_headline":"Molina Healthcare beats expectations on disciplined cost management","gap_size":"Big","outcome_label":"Pending","summary":"On April 23, 2026, Molina Healthcare jumped 7.7% because it beat earnings expectations.","has_analysis":false},{"ticker":"MCHP","name":"Microchip Technology","sector":"Information Technology","signal_date":"2026-04-23","gap_up_pct":4.04,"selloff_pct":1.73,"outcome_1d":null,"outcome_5d":null,"outcome_10d":null,"signal_strength":29,"status":"active","catalyst_type":null,"catalyst_headline":null,"gap_size":"Medium","outcome_label":"Pending","summary":"On April 23, 2026, Microchip Technology jumped 4.0% because of big news.","has_analysis":false},{"ticker":"HAS","name":"Hasbro","sector":"Consumer Discretionary","signal_date":"2026-04-23","gap_up_pct":4.84,"selloff_pct":2.64,"outcome_1d":null,"outcome_5d":null,"outcome_10d":null,"signal_strength":62,"status":"active","catalyst_type":"earnings_beat","catalyst_headline":"Hasbro shares jump on preliminary Q1 revenue beat despite cyber incident","gap_size":"Medium","outcome_label":"Pending","summary":"On April 23, 2026, Hasbro jumped 4.8% because it beat earnings expectations.","has_analysis":false},{"ticker":"GEV","name":"GE Vernova","sector":"Industrials","signal_date":"2026-04-23","gap_up_pct":1.8,"selloff_pct":2.74,"outcome_1d":null,"outcome_5d":null,"outcome_10d":null,"signal_strength":33,"status":"active","catalyst_type":"positive_news","catalyst_headline":"Inside GE Vernova’s 90% Surge","gap_size":"Small","outcome_label":"Pending","summary":"On April 23, 2026, GE Vernova jumped 1.8% because of positive news.","has_analysis":false},{"ticker":"FANG","name":"Diamondback Energy","sector":"Energy","signal_date":"2026-04-23","gap_up_pct":1.52,"selloff_pct":1.31,"outcome_1d":null,"outcome_5d":null,"outcome_10d":null,"signal_strength":34,"status":"active","catalyst_type":"upgrade","catalyst_headline":"Scotiabank Maintains Sector Outperform on Diamondback Energy, Raises Price Target to $195","gap_size":"Small","outcome_label":"Pending","summary":"On April 23, 2026, Diamondback Energy jumped 1.5% because an analyst upgraded the stock.","has_analysis":false},{"ticker":"DOV","name":"Dover Corporation","sector":"Industrials","signal_date":"2026-04-23","gap_up_pct":2.98,"selloff_pct":1.96,"outcome_1d":null,"outcome_5d":null,"outcome_10d":null,"signal_strength":50,"status":"active","catalyst_type":"earnings_beat","catalyst_headline":"Dover Q1 Earnings Beat Estimates, Rise Y/Y on Solid Demand","gap_size":"Small","outcome_label":"Pending","summary":"On April 23, 2026, Dover Corporation jumped 3.0% because it beat earnings expectations.","has_analysis":false},{"ticker":"CMCSA","name":"Comcast","sector":"Communication Services","signal_date":"2026-04-23","gap_up_pct":3.85,"selloff_pct":1.37,"outcome_1d":null,"outcome_5d":null,"outcome_10d":null,"signal_strength":51,"status":"active","catalyst_type":"earnings_beat","catalyst_headline":"Comcast broadband and wireless gains drive earnings beat, shares jump","gap_size":"Medium","outcome_label":"Pending","summary":"On April 23, 2026, Comcast jumped 3.9% because it beat earnings expectations.","has_analysis":false},{"ticker":"CHTR","name":"Charter Communications","sector":"Communication Services","signal_date":"2026-04-23","gap_up_pct":2.83,"selloff_pct":4.85,"outcome_1d":null,"outcome_5d":null,"outcome_10d":null,"signal_strength":38,"status":"active","catalyst_type":null,"catalyst_headline":null,"gap_size":"Small","outcome_label":"Pending","summary":"On April 23, 2026, Charter Communications jumped 2.8% because of big news.","has_analysis":false},{"ticker":"CF","name":"CF Industries","sector":"Materials","signal_date":"2026-04-23","gap_up_pct":1.5,"selloff_pct":1.48,"outcome_1d":null,"outcome_5d":null,"outcome_10d":null,"signal_strength":15,"status":"active","catalyst_type":null,"catalyst_headline":null,"gap_size":"Small","outcome_label":"Pending","summary":"On April 23, 2026, CF Industries jumped 1.5% because of big news.","has_analysis":false},{"ticker":"CCI","name":"Crown Castle","sector":"Real Estate","signal_date":"2026-04-23","gap_up_pct":3.36,"selloff_pct":2.41,"outcome_1d":null,"outcome_5d":null,"outcome_10d":null,"signal_strength":54,"status":"active","catalyst_type":"earnings_beat","catalyst_headline":"Crown Castle Q1 AFFO & Sales Beat Estimates Despite DISH Headwinds","gap_size":"Medium","outcome_label":"Pending","summary":"On April 23, 2026, Crown Castle jumped 3.4% because it beat earnings expectations.","has_analysis":false},{"ticker":"CBRE","name":"CBRE Group","sector":"Real Estate","signal_date":"2026-04-23","gap_up_pct":2.27,"selloff_pct":5.26,"outcome_1d":null,"outcome_5d":null,"outcome_10d":null,"signal_strength":61,"status":"active","catalyst_type":"earnings_beat","catalyst_headline":"CBRE's Q1 Earnings Beat Estimates on Solid Leasing & Capital Markets","gap_size":"Small","outcome_label":"Pending","summary":"On April 23, 2026, CBRE Group jumped 2.3% because it beat earnings expectations.","has_analysis":false},{"ticker":"ADI","name":"Analog Devices","sector":"Information Technology","signal_date":"2026-04-23","gap_up_pct":4.32,"selloff_pct":1.1,"outcome_1d":null,"outcome_5d":null,"outcome_10d":null,"signal_strength":52,"status":"active","catalyst_type":"earnings_beat","catalyst_headline":"Analog Devices (ADI) Beats Stock Market Upswing: What Investors Need to Know","gap_size":"Medium","outcome_label":"Pending","summary":"On April 23, 2026, Analog Devices jumped 4.3% because it beat earnings expectations.","has_analysis":false},{"ticker":"WDC","name":"Western Digital","sector":"Information Technology","signal_date":"2026-04-22","gap_up_pct":3.85,"selloff_pct":3.21,"outcome_1d":null,"outcome_5d":null,"outcome_10d":null,"signal_strength":55,"status":"active","catalyst_type":"upgrade","catalyst_headline":"Seagate Stock Upgraded To Buy Rating. Here's Why There Is 'Another Leg' To AI-Fueled Rally.","gap_size":"Medium","outcome_label":"Pending","summary":"On April 22, 2026, Western Digital jumped 3.9% because an analyst upgraded the stock.","has_analysis":false},{"ticker":"VST","name":"Vistra Corp.","sector":"Utilities","signal_date":"2026-04-22","gap_up_pct":1.87,"selloff_pct":2.07,"outcome_1d":null,"outcome_5d":null,"outcome_10d":null,"signal_strength":20,"status":"active","catalyst_type":null,"catalyst_headline":null,"gap_size":"Small","outcome_label":"Pending","summary":"On April 22, 2026, Vistra Corp. jumped 1.9% because of big news.","has_analysis":false},{"ticker":"TPL","name":"Texas Pacific Land Corporation","sector":"Energy","signal_date":"2026-04-22","gap_up_pct":1.89,"selloff_pct":2.12,"outcome_1d":null,"outcome_5d":null,"outcome_10d":null,"signal_strength":20,"status":"active","catalyst_type":null,"catalyst_headline":null,"gap_size":"Small","outcome_label":"Pending","summary":"On April 22, 2026, Texas Pacific Land Corporation jumped 1.9% because of big news.","has_analysis":false},{"ticker":"TER","name":"Teradyne","sector":"Information Technology","signal_date":"2026-04-22","gap_up_pct":2.36,"selloff_pct":1.44,"outcome_1d":null,"outcome_5d":null,"outcome_10d":null,"signal_strength":39,"status":"active","catalyst_type":"upgrade","catalyst_headline":"UBS Maintains Buy on Teradyne, Raises Price Target to $440","gap_size":"Small","outcome_label":"Pending","summary":"On April 22, 2026, Teradyne jumped 2.4% because an analyst upgraded the stock.","has_analysis":false},{"ticker":"TDY","name":"Teledyne Technologies","sector":"Information Technology","signal_date":"2026-04-22","gap_up_pct":3.46,"selloff_pct":4.41,"outcome_1d":null,"outcome_5d":null,"outcome_10d":null,"signal_strength":69,"status":"active","catalyst_type":"earnings_beat","catalyst_headline":"Teledyne's Q1 Earnings & Revenues Beat Estimates, '26 EPS View Raised","gap_size":"Medium","outcome_label":"Pending","summary":"On April 22, 2026, Teledyne Technologies jumped 3.5% because it beat earnings expectations.","has_analysis":false},{"ticker":"STX","name":"Seagate Technology","sector":"Information Technology","signal_date":"2026-04-22","gap_up_pct":3.59,"selloff_pct":1.04,"outcome_1d":null,"outcome_5d":null,"outcome_10d":null,"signal_strength":43,"status":"active","catalyst_type":"upgrade","catalyst_headline":"Airbnb upgraded, Zscaler downgraded: Wall Street's top analyst calls","gap_size":"Medium","outcome_label":"Pending","summary":"On April 22, 2026, Seagate Technology jumped 3.6% because an analyst upgraded the stock.","has_analysis":false},{"ticker":"SHW","name":"Sherwin-Williams","sector":"Materials","signal_date":"2026-04-22","gap_up_pct":1.51,"selloff_pct":2.14,"outcome_1d":null,"outcome_5d":null,"outcome_10d":null,"signal_strength":18,"status":"active","catalyst_type":null,"catalyst_headline":null,"gap_size":"Small","outcome_label":"Pending","summary":"On April 22, 2026, Sherwin-Williams jumped 1.5% because of big news.","has_analysis":false},{"ticker":"SHOP","name":"Shopify","sector":"","signal_date":"2026-04-22","gap_up_pct":1.72,"selloff_pct":1.35,"outcome_1d":null,"outcome_5d":null,"outcome_10d":null,"signal_strength":15,"status":"active","catalyst_type":null,"catalyst_headline":null,"gap_size":"Small","outcome_label":"Pending","summary":"On April 22, 2026, Shopify jumped 1.7% because of big news.","has_analysis":false},{"ticker":"SBAC","name":"SBA Communications","sector":"Real Estate","signal_date":"2026-04-22","gap_up_pct":1.83,"selloff_pct":3.14,"outcome_1d":null,"outcome_5d":null,"outcome_10d":null,"signal_strength":45,"status":"active","catalyst_type":"upgrade","catalyst_headline":"This Airbnb Analyst Turns Bullish; Here Are Top 4 Upgrades For Wednesday","gap_size":"Small","outcome_label":"Pending","summary":"On April 22, 2026, SBA Communications jumped 1.8% because an analyst upgraded the stock.","has_analysis":false},{"ticker":"SATS","name":"EchoStar","sector":"Communication Services","signal_date":"2026-04-22","gap_up_pct":2.35,"selloff_pct":3.94,"outcome_1d":null,"outcome_5d":null,"outcome_10d":null,"signal_strength":41,"status":"active","catalyst_type":"positive_news","catalyst_headline":"Is It Too Late To Consider EchoStar (SATS) After Its Multi Year Surge?","gap_size":"Small","outcome_label":"Pending","summary":"On April 22, 2026, EchoStar jumped 2.4% because of positive news.","has_analysis":false},{"ticker":"NXPI","name":"NXP Semiconductors","sector":"Information Technology","signal_date":"2026-04-22","gap_up_pct":1.78,"selloff_pct":1.39,"outcome_1d":null,"outcome_5d":null,"outcome_10d":null,"signal_strength":23,"status":"active","catalyst_type":null,"catalyst_headline":null,"gap_size":"Small","outcome_label":"Pending","summary":"On April 22, 2026, NXP Semiconductors jumped 1.8% because of big news.","has_analysis":false},{"ticker":"MSTR","name":"MicroStrategy","sector":"","signal_date":"2026-04-22","gap_up_pct":6.68,"selloff_pct":2.12,"outcome_1d":null,"outcome_5d":null,"outcome_10d":null,"signal_strength":46,"status":"active","catalyst_type":"positive_news","catalyst_headline":"Bitcoin, Ethereum Rally, XRP, Dogecoin Hold Steady Amid Brewing Strait Of Hormuz Tensions: Analyst Sees BTC's Real Rally After A Small 'Breather'","gap_size":"Big","outcome_label":"Pending","summary":"On April 22, 2026, MicroStrategy jumped 6.7% because of positive news.","has_analysis":false},{"ticker":"MSCI","name":"MSCI Inc.","sector":"Financials","signal_date":"2026-04-22","gap_up_pct":1.78,"selloff_pct":2.13,"outcome_1d":null,"outcome_5d":null,"outcome_10d":null,"signal_strength":43,"status":"active","catalyst_type":"upgrade","catalyst_headline":"UBS Maintains Buy on MSCI, Raises Price Target to $720","gap_size":"Small","outcome_label":"Pending","summary":"On April 22, 2026, MSCI Inc. jumped 1.8% because an analyst upgraded the stock.","has_analysis":false},{"ticker":"MOH","name":"Molina Healthcare","sector":"Health Care","signal_date":"2026-04-22","gap_up_pct":1.58,"selloff_pct":1.74,"outcome_1d":null,"outcome_5d":null,"outcome_10d":null,"signal_strength":66,"status":"active","catalyst_type":"earnings_beat","catalyst_headline":"Molina Healthcare beats quarterly profit estimates on controlled medical costs","gap_size":"Small","outcome_label":"Pending","summary":"On April 22, 2026, Molina Healthcare jumped 1.6% because it beat earnings expectations.","has_analysis":false},{"ticker":"MCO","name":"Moody's Corporation","sector":"Financials","signal_date":"2026-04-22","gap_up_pct":3.19,"selloff_pct":3.28,"outcome_1d":null,"outcome_5d":null,"outcome_10d":null,"signal_strength":57,"status":"active","catalyst_type":"earnings_beat","catalyst_headline":"MCO Q1 Earnings Beat on Rising Analytics Demand & Higher Issuances","gap_size":"Medium","outcome_label":"Pending","summary":"On April 22, 2026, Moody's Corporation jumped 3.2% because it beat earnings expectations.","has_analysis":false},{"ticker":"MAS","name":"Masco","sector":"Industrials","signal_date":"2026-04-22","gap_up_pct":11.1,"selloff_pct":2.81,"outcome_1d":null,"outcome_5d":null,"outcome_10d":null,"signal_strength":74,"status":"active","catalyst_type":"earnings_beat","catalyst_headline":"Masco Stock Tops the S&P 500’s Winners. What Solid Earnings Say About Housing.","gap_size":"Huge","outcome_label":"Pending","summary":"On April 22, 2026, Masco jumped 11.1% because it beat earnings expectations.","has_analysis":false},{"ticker":"KLAC","name":"KLA Corporation","sector":"Information Technology","signal_date":"2026-04-22","gap_up_pct":1.55,"selloff_pct":0.13,"outcome_1d":null,"outcome_5d":null,"outcome_10d":null,"signal_strength":35,"status":"active","catalyst_type":"earnings_beat","catalyst_headline":"KLA (KLAC) Exceeds Market Returns: Some Facts to Consider","gap_size":"Small","outcome_label":"Pending","summary":"On April 22, 2026, KLA Corporation jumped 1.6% because it beat earnings expectations.","has_analysis":false},{"ticker":"KKR","name":"KKR & Co.","sector":"Financials","signal_date":"2026-04-22","gap_up_pct":2.07,"selloff_pct":1.61,"outcome_1d":null,"outcome_5d":null,"outcome_10d":null,"signal_strength":38,"status":"active","catalyst_type":"upgrade","catalyst_headline":"Morgan Stanley Maintains Overweight on KKR, Lowers Price Target to $153","gap_size":"Small","outcome_label":"Pending","summary":"On April 22, 2026, KKR & Co. jumped 2.1% because an analyst upgraded the stock.","has_analysis":false},{"ticker":"ISRG","name":"Intuitive Surgical","sector":"Health Care","signal_date":"2026-04-22","gap_up_pct":2.23,"selloff_pct":1.53,"outcome_1d":null,"outcome_5d":null,"outcome_10d":null,"signal_strength":49,"status":"active","catalyst_type":"earnings_beat","catalyst_headline":"Intuitive Surgical Reports Another Blowout Quarter: Time to Buy the Stock?","gap_size":"Small","outcome_label":"Pending","summary":"On April 22, 2026, Intuitive Surgical jumped 2.2% because it beat earnings expectations.","has_analysis":false},{"ticker":"IQV","name":"IQVIA","sector":"Health Care","signal_date":"2026-04-22","gap_up_pct":1.5,"selloff_pct":2.51,"outcome_1d":null,"outcome_5d":null,"outcome_10d":null,"signal_strength":25,"status":"active","catalyst_type":null,"catalyst_headline":null,"gap_size":"Small","outcome_label":"Pending","summary":"On April 22, 2026, IQVIA jumped 1.5% because of big news.","has_analysis":false},{"ticker":"INTC","name":"Intel","sector":"Information Technology","signal_date":"2026-04-22","gap_up_pct":2.54,"selloff_pct":5.09,"outcome_1d":null,"outcome_5d":null,"outcome_10d":null,"signal_strength":50,"status":"active","catalyst_type":"positive_news","catalyst_headline":"After Costco's Surge, Here Are the 3 Best S&P 500 Stocks to Buy Now","gap_size":"Small","outcome_label":"Pending","summary":"On April 22, 2026, Intel jumped 2.5% because of positive news.","has_analysis":false},{"ticker":"HOOD","name":"Robinhood Markets","sector":"Financials","signal_date":"2026-04-22","gap_up_pct":3.38,"selloff_pct":1.89,"outcome_1d":null,"outcome_5d":null,"outcome_10d":null,"signal_strength":51,"status":"active","catalyst_type":"earnings_beat","catalyst_headline":"Robinhood Markets, Inc. (HOOD) Beats Stock Market Upswing: What Investors Need to Know","gap_size":"Medium","outcome_label":"Pending","summary":"On April 22, 2026, Robinhood Markets jumped 3.4% because it beat earnings expectations.","has_analysis":false},{"ticker":"HAL","name":"Halliburton","sector":"Energy","signal_date":"2026-04-22","gap_up_pct":2.25,"selloff_pct":1.06,"outcome_1d":null,"outcome_5d":null,"outcome_10d":null,"signal_strength":42,"status":"active","catalyst_type":"earnings_beat","catalyst_headline":"Halliburton Q1 Beats Expectations on Strong International Growth, Morgan Stanley Says","gap_size":"Small","outcome_label":"Pending","summary":"On April 22, 2026, Halliburton jumped 2.2% because it beat earnings expectations.","has_analysis":false},{"ticker":"GNRC","name":"Generac","sector":"Industrials","signal_date":"2026-04-22","gap_up_pct":2.16,"selloff_pct":2.67,"outcome_1d":null,"outcome_5d":null,"outcome_10d":null,"signal_strength":24,"status":"active","catalyst_type":null,"catalyst_headline":null,"gap_size":"Small","outcome_label":"Pending","summary":"On April 22, 2026, Generac jumped 2.2% because of big news.","has_analysis":false},{"ticker":"GLW","name":"Corning Inc.","sector":"Information Technology","signal_date":"2026-04-22","gap_up_pct":1.54,"selloff_pct":2.42,"outcome_1d":null,"outcome_5d":null,"outcome_10d":null,"signal_strength":45,"status":"active","catalyst_type":"earnings_beat","catalyst_headline":"TEL Q2 Earnings Beat Estimates on Record Orders & Margin Gains","gap_size":"Small","outcome_label":"Pending","summary":"On April 22, 2026, Corning Inc. jumped 1.5% because it beat earnings expectations.","has_analysis":false},{"ticker":"GEV","name":"GE Vernova","sector":"Industrials","signal_date":"2026-04-22","gap_up_pct":8.56,"selloff_pct":1.26,"outcome_1d":null,"outcome_5d":null,"outcome_10d":null,"signal_strength":59,"status":"active","catalyst_type":"earnings_beat","catalyst_headline":"US Equity Indexes Jump as Iran Ceasefire Extension, Strong Earnings Help Lift Sentiment","gap_size":"Big","outcome_label":"Pending","summary":"On April 22, 2026, GE Vernova jumped 8.6% because it beat earnings expectations.","has_analysis":false},{"ticker":"FICO","name":"Fair Isaac","sector":"Information Technology","signal_date":"2026-04-22","gap_up_pct":1.63,"selloff_pct":9.29,"outcome_1d":null,"outcome_5d":null,"outcome_10d":null,"signal_strength":57,"status":"active","catalyst_type":"upgrade","catalyst_headline":"Mizuho Initiates Coverage of Fair Isaac (FICO) with Outperform Rating","gap_size":"Small","outcome_label":"Pending","summary":"On April 22, 2026, Fair Isaac jumped 1.6% because an analyst upgraded the stock.","has_analysis":false},{"ticker":"ETN","name":"Eaton Corporation","sector":"Industrials","signal_date":"2026-04-22","gap_up_pct":1.86,"selloff_pct":1.34,"outcome_1d":null,"outcome_5d":null,"outcome_10d":null,"signal_strength":30,"status":"active","catalyst_type":"positive_news","catalyst_headline":"Eaton (ETN) Gains But Lags Market: What You Should Know","gap_size":"Small","outcome_label":"Pending","summary":"On April 22, 2026, Eaton Corporation jumped 1.9% because of positive news.","has_analysis":false}]}