{"categories":[{"move_size":"Minor","total_events":244,"avg_gap_pct":2.02,"avg_selloff_pct":2.23,"avg_return_1d":0.55,"win_rate_1d":55.0,"avg_return_5d":0.86,"win_rate_5d":46.2,"avg_return_10d":2.79,"win_rate_10d":53.3,"avg_intraday_peak_pct":1.61,"avg_intraday_dip_pct":2.23,"avg_next_day_recovery_pct":0.57,"avg_strength":33.4,"description":"Small price jumps (1.5-3%) — happens often, usually after analyst comments or minor news","emoji":"📊"},{"move_size":"Medium","total_events":53,"avg_gap_pct":3.67,"avg_selloff_pct":2.67,"avg_return_1d":0.23,"win_rate_1d":48.1,"avg_return_5d":2.41,"win_rate_5d":43.3,"avg_return_10d":10.13,"win_rate_10d":100.0,"avg_intraday_peak_pct":2.3,"avg_intraday_dip_pct":2.67,"avg_next_day_recovery_pct":-0.1,"avg_strength":48.2,"description":"Noticeable jumps (3-5%) — often triggered by solid earnings or analyst upgrades","emoji":"📈"},{"move_size":"Large","total_events":25,"avg_gap_pct":6.88,"avg_selloff_pct":3.41,"avg_return_1d":-0.85,"win_rate_1d":47.8,"avg_return_5d":-1.35,"win_rate_5d":35.3,"avg_return_10d":1.82,"win_rate_10d":100.0,"avg_intraday_peak_pct":2.72,"avg_intraday_dip_pct":3.41,"avg_next_day_recovery_pct":-0.35,"avg_strength":59.2,"description":"Big moves (5-10%) — usually means surprisingly good earnings or a major announcement","emoji":"🚀"},{"move_size":"Major","total_events":4,"avg_gap_pct":14.18,"avg_selloff_pct":2.69,"avg_return_1d":-1.7,"win_rate_1d":50.0,"avg_return_5d":null,"win_rate_5d":null,"avg_return_10d":null,"win_rate_10d":null,"avg_intraday_peak_pct":3.77,"avg_intraday_dip_pct":2.69,"avg_next_day_recovery_pct":-0.0,"avg_strength":70.5,"description":"Huge moves (10%+) — blockbuster earnings beats or game-changing news","emoji":"💥"}],"totals":{"total":326,"avg_gap":2.81,"avg_return_1d":0.34,"win_rate_1d":53.0}}