{"categories":[{"move_size":"Minor","total_events":135,"avg_gap_pct":2.06,"avg_selloff_pct":2.04,"avg_return_1d":2.65,"win_rate_1d":79.5,"avg_return_5d":null,"win_rate_5d":null,"avg_return_10d":null,"win_rate_10d":null,"avg_intraday_peak_pct":1.88,"avg_intraday_dip_pct":2.04,"avg_next_day_recovery_pct":1.16,"avg_strength":31.3,"description":"Small price jumps (1.5-3%) — happens often, usually after analyst comments or minor news","emoji":"📊"},{"move_size":"Medium","total_events":23,"avg_gap_pct":3.62,"avg_selloff_pct":2.6,"avg_return_1d":3.37,"win_rate_1d":83.3,"avg_return_5d":null,"win_rate_5d":null,"avg_return_10d":null,"win_rate_10d":null,"avg_intraday_peak_pct":2.39,"avg_intraday_dip_pct":2.6,"avg_next_day_recovery_pct":1.43,"avg_strength":43.5,"description":"Noticeable jumps (3-5%) — often triggered by solid earnings or analyst upgrades","emoji":"📈"},{"move_size":"Large","total_events":14,"avg_gap_pct":6.63,"avg_selloff_pct":4.03,"avg_return_1d":3.67,"win_rate_1d":80.0,"avg_return_5d":null,"win_rate_5d":null,"avg_return_10d":null,"win_rate_10d":null,"avg_intraday_peak_pct":1.96,"avg_intraday_dip_pct":4.03,"avg_next_day_recovery_pct":-0.17,"avg_strength":60.5,"description":"Big moves (5-10%) — usually means surprisingly good earnings or a major announcement","emoji":"🚀"}],"totals":{"total":172,"avg_gap":2.64,"avg_return_1d":2.87,"win_rate_1d":80.3}}