{"days":90,"sectors":[{"sector":"Information Technology","total_events":571,"avg_gap":3.59,"avg_return_1d":0.54,"win_rate_1d":51.2,"avg_selloff":2.93,"big_moves":81},{"sector":"Industrials","total_events":248,"avg_gap":2.78,"avg_return_1d":-0.55,"win_rate_1d":41.2,"avg_selloff":2.23,"big_moves":22},{"sector":"Consumer Discretionary","total_events":149,"avg_gap":2.87,"avg_return_1d":-1.57,"win_rate_1d":37.5,"avg_selloff":2.58,"big_moves":13},{"sector":"Financials","total_events":118,"avg_gap":2.43,"avg_return_1d":-0.15,"win_rate_1d":48.3,"avg_selloff":2.36,"big_moves":5},{"sector":"Health Care","total_events":111,"avg_gap":2.77,"avg_return_1d":0.18,"win_rate_1d":51.0,"avg_selloff":2.39,"big_moves":10},{"sector":"","total_events":105,"avg_gap":3.41,"avg_return_1d":-0.32,"win_rate_1d":42.6,"avg_selloff":2.99,"big_moves":17},{"sector":"Materials","total_events":90,"avg_gap":2.65,"avg_return_1d":0.09,"win_rate_1d":40.7,"avg_selloff":2.66,"big_moves":6},{"sector":"Consumer Staples","total_events":52,"avg_gap":3.43,"avg_return_1d":1.06,"win_rate_1d":67.4,"avg_selloff":2.23,"big_moves":9},{"sector":"Communication Services","total_events":40,"avg_gap":2.6,"avg_return_1d":-1.37,"win_rate_1d":48.7,"avg_selloff":3.31,"big_moves":3},{"sector":"Energy","total_events":34,"avg_gap":2.05,"avg_return_1d":0.42,"win_rate_1d":52.9,"avg_selloff":2.18,"big_moves":0},{"sector":"Real Estate","total_events":31,"avg_gap":2.02,"avg_return_1d":0.06,"win_rate_1d":58.6,"avg_selloff":2.36,"big_moves":0},{"sector":"Utilities","total_events":17,"avg_gap":2.8,"avg_return_1d":-1.18,"win_rate_1d":41.2,"avg_selloff":2.81,"big_moves":1}]}