[{"ticker":"NVR","name":"NVR, Inc.","sector":"Consumer Discretionary","industry":"Homebuilding","market_cap":null,"exchange":"NYSE/NASDAQ","close":6389.5698,"prev_close":6352.5498,"change_pct":0.5828,"rsi_14":null,"sma_50":null,"sma_200":null,"bb_pctb":null,"above_sma50":null,"above_sma200":null},{"ticker":"AZO","name":"AutoZone","sector":"Consumer Discretionary","industry":"Automotive Retail","market_cap":null,"exchange":"NYSE/NASDAQ","close":3046.46,"prev_close":2949.0601,"change_pct":3.3027,"rsi_14":null,"sma_50":null,"sma_200":null,"bb_pctb":null,"above_sma50":null,"above_sma200":null},{"ticker":"SNDK","name":"Sandisk","sector":"Information Technology","industry":"Technology Hardware, Storage & Peripherals","market_cap":null,"exchange":"NYSE/NASDAQ","close":1963.6,"prev_close":2273.73,"change_pct":-13.6397,"rsi_14":null,"sma_50":null,"sma_200":null,"bb_pctb":null,"above_sma50":null,"above_sma200":null},{"ticker":"FIX","name":"Comfort Systems USA","sector":"Industrials","industry":"Construction & Engineering","market_cap":null,"exchange":"NYSE/NASDAQ","close":1908.0699,"prev_close":2066.51,"change_pct":-7.667,"rsi_14":null,"sma_50":null,"sma_200":null,"bb_pctb":null,"above_sma50":null,"above_sma200":null},{"ticker":"ASML","name":"ASML Holding","sector":"","industry":"","market_cap":null,"exchange":"NMS","close":1778.46,"prev_close":1929.25,"change_pct":-7.816,"rsi_14":null,"sma_50":null,"sma_200":null,"bb_pctb":null,"above_sma50":null,"above_sma200":null},{"ticker":"MELI","name":"Mercado Libre","sector":"","industry":"","market_cap":null,"exchange":"NMS","close":1583.66,"prev_close":1589.45,"change_pct":-0.3643,"rsi_14":null,"sma_50":null,"sma_200":null,"bb_pctb":null,"above_sma50":null,"above_sma200":null},{"ticker":"MPWR","name":"Monolithic Power Systems","sector":"Information Technology","industry":"Semiconductors","market_cap":null,"exchange":"NYSE/NASDAQ","close":1423.76,"prev_close":1537.88,"change_pct":-7.4206,"rsi_14":null,"sma_50":null,"sma_200":null,"bb_pctb":null,"above_sma50":null,"above_sma200":null},{"ticker":"GWW","name":"W. W. Grainger","sector":"Industrials","industry":"Industrial Machinery & Supplies & Components","market_cap":null,"exchange":"NYSE/NASDAQ","close":1320.48,"prev_close":1341.42,"change_pct":-1.561,"rsi_14":null,"sma_50":null,"sma_200":null,"bb_pctb":null,"above_sma50":null,"above_sma200":null},{"ticker":"TDG","name":"TransDigm Group","sector":"Industrials","industry":"Aerospace & Defense","market_cap":null,"exchange":"NYSE/NASDAQ","close":1297.6801,"prev_close":1295.9,"change_pct":0.1374,"rsi_14":null,"sma_50":null,"sma_200":null,"bb_pctb":null,"above_sma50":null,"above_sma200":null},{"ticker":"MTD","name":"Mettler Toledo","sector":"Health Care","industry":"Life Sciences Tools & Services","market_cap":null,"exchange":"NYSE/NASDAQ","close":1156.64,"prev_close":1164.0699,"change_pct":-0.6383,"rsi_14":null,"sma_50":null,"sma_200":null,"bb_pctb":null,"above_sma50":null,"above_sma200":null},{"ticker":"EQIX","name":"Equinix","sector":"Real Estate","industry":"Data Center REITs","market_cap":null,"exchange":"NYSE/NASDAQ","close":1115.9301,"prev_close":1115.9399,"change_pct":-0.0009,"rsi_14":null,"sma_50":null,"sma_200":null,"bb_pctb":null,"above_sma50":null,"above_sma200":null},{"ticker":"LLY","name":"Lilly (Eli)","sector":"Health Care","industry":"Pharmaceuticals","market_cap":null,"exchange":"NYSE/NASDAQ","close":1107.08,"prev_close":1102.08,"change_pct":0.4537,"rsi_14":null,"sma_50":null,"sma_200":null,"bb_pctb":null,"above_sma50":null,"above_sma200":null},{"ticker":"FICO","name":"Fair Isaac","sector":"Information Technology","industry":"Application Software","market_cap":null,"exchange":"NYSE/NASDAQ","close":1099.41,"prev_close":1090.85,"change_pct":0.7847,"rsi_14":null,"sma_50":null,"sma_200":null,"bb_pctb":null,"above_sma50":null,"above_sma200":null},{"ticker":"GS","name":"Goldman Sachs","sector":"Financials","industry":"Investment Banking & Brokerage","market_cap":null,"exchange":"NYSE/NASDAQ","close":1094.4399,"prev_close":1106.37,"change_pct":-1.0783,"rsi_14":null,"sma_50":null,"sma_200":null,"bb_pctb":null,"above_sma50":null,"above_sma200":null},{"ticker":"URI","name":"United Rentals","sector":"Industrials","industry":"Trading Companies & Distributors","market_cap":null,"exchange":"NYSE/NASDAQ","close":1063.14,"prev_close":1092.6801,"change_pct":-2.7034,"rsi_14":null,"sma_50":null,"sma_200":null,"bb_pctb":null,"above_sma50":null,"above_sma200":null},{"ticker":"MU","name":"Micron Technology","sector":"Information Technology","industry":"Semiconductors","market_cap":null,"exchange":"NYSE/NASDAQ","close":1051.77,"prev_close":1211.38,"change_pct":-13.1759,"rsi_14":null,"sma_50":null,"sma_200":null,"bb_pctb":null,"above_sma50":null,"above_sma200":null},{"ticker":"STX","name":"Seagate Technology","sector":"Information Technology","industry":"Technology Hardware, Storage & Peripherals","market_cap":null,"exchange":"NYSE/NASDAQ","close":1038.59,"prev_close":1094.04,"change_pct":-5.0684,"rsi_14":null,"sma_50":null,"sma_200":null,"bb_pctb":null,"above_sma50":null,"above_sma200":null},{"ticker":"GEV","name":"GE Vernova","sector":"Industrials","industry":"Heavy Electrical Equipment","market_cap":null,"exchange":"NYSE/NASDAQ","close":1034.98,"prev_close":1127.59,"change_pct":-8.2131,"rsi_14":null,"sma_50":null,"sma_200":null,"bb_pctb":null,"above_sma50":null,"above_sma200":null},{"ticker":"BLK","name":"BlackRock","sector":"Financials","industry":"Asset Management & Custody Banks","market_cap":null,"exchange":"NYSE/NASDAQ","close":1015.33,"prev_close":1051.74,"change_pct":-3.4619,"rsi_14":null,"sma_50":null,"sma_200":null,"bb_pctb":null,"above_sma50":null,"above_sma200":null},{"ticker":"CAT","name":"Caterpillar Inc.","sector":"Industrials","industry":"Construction Machinery & Heavy Transportation Equipment","market_cap":null,"exchange":"NYSE/NASDAQ","close":984.24,"prev_close":1022.28,"change_pct":-3.7211,"rsi_14":null,"sma_50":null,"sma_200":null,"bb_pctb":null,"above_sma50":null,"above_sma200":null},{"ticker":"COST","name":"Costco","sector":"Consumer Staples","industry":"Consumer Staples Merchandise Retail","market_cap":null,"exchange":"NYSE/NASDAQ","close":957.68,"prev_close":951.35,"change_pct":0.6654,"rsi_14":null,"sma_50":null,"sma_200":null,"bb_pctb":null,"above_sma50":null,"above_sma200":null},{"ticker":"PH","name":"Parker Hannifin","sector":"Industrials","industry":"Industrial Machinery & Supplies & Components","market_cap":null,"exchange":"NYSE/NASDAQ","close":947.58,"prev_close":962.14,"change_pct":-1.5133,"rsi_14":null,"sma_50":null,"sma_200":null,"bb_pctb":null,"above_sma50":null,"above_sma200":null},{"ticker":"EME","name":"Emcor","sector":"Industrials","industry":"Construction & Engineering","market_cap":null,"exchange":"NYSE/NASDAQ","close":838.61,"prev_close":868.88,"change_pct":-3.4838,"rsi_14":null,"sma_50":null,"sma_200":null,"bb_pctb":null,"above_sma50":null,"above_sma200":null},{"ticker":"CASY","name":"Casey's","sector":"Consumer Staples","industry":"Food Retail","market_cap":null,"exchange":"NYSE/NASDAQ","close":831.89,"prev_close":831.67,"change_pct":0.0265,"rsi_14":null,"sma_50":null,"sma_200":null,"bb_pctb":null,"above_sma50":null,"above_sma200":null},{"ticker":"LITE","name":"Lumentum","sector":"Information Technology","industry":"Communications Equipment","market_cap":null,"exchange":"NYSE/NASDAQ","close":827.92,"prev_close":893.93,"change_pct":-7.3842,"rsi_14":null,"sma_50":null,"sma_200":null,"bb_pctb":null,"above_sma50":null,"above_sma200":null},{"ticker":"MCK","name":"McKesson Corporation","sector":"Health Care","industry":"Health Care Distributors","market_cap":null,"exchange":"NYSE/NASDAQ","close":763.91,"prev_close":744.85,"change_pct":2.5589,"rsi_14":null,"sma_50":null,"sma_200":null,"bb_pctb":null,"above_sma50":null,"above_sma200":null},{"ticker":"PWR","name":"Quanta Services","sector":"Industrials","industry":"Construction & Engineering","market_cap":null,"exchange":"NYSE/NASDAQ","close":702.29,"prev_close":740.14,"change_pct":-5.1139,"rsi_14":null,"sma_50":null,"sma_200":null,"bb_pctb":null,"above_sma50":null,"above_sma200":null},{"ticker":"CMI","name":"Cummins","sector":"Industrials","industry":"Construction Machinery & Heavy Transportation Equipment","market_cap":null,"exchange":"NYSE/NASDAQ","close":699.05,"prev_close":724.93,"change_pct":-3.57,"rsi_14":null,"sma_50":null,"sma_200":null,"bb_pctb":null,"above_sma50":null,"above_sma200":null},{"ticker":"CRWD","name":"CrowdStrike","sector":"Information Technology","industry":"Systems Software","market_cap":null,"exchange":"NYSE/NASDAQ","close":680.92,"prev_close":675.44,"change_pct":0.8113,"rsi_14":null,"sma_50":null,"sma_200":null,"bb_pctb":null,"above_sma50":null,"above_sma200":null},{"ticker":"WDC","name":"Western Digital","sector":"Information Technology","industry":"Technology Hardware, Storage & Peripherals","market_cap":null,"exchange":"NYSE/NASDAQ","close":670.75,"prev_close":732.62,"change_pct":-8.445,"rsi_14":null,"sma_50":null,"sma_200":null,"bb_pctb":null,"above_sma50":null,"above_sma200":null},{"ticker":"REGN","name":"Regeneron Pharmaceuticals","sector":"Health Care","industry":"Biotechnology","market_cap":null,"exchange":"NYSE/NASDAQ","close":618.03,"prev_close":612.5,"change_pct":0.9029,"rsi_14":null,"sma_50":null,"sma_200":null,"bb_pctb":null,"above_sma50":null,"above_sma200":null},{"ticker":"TDY","name":"Teledyne Technologies","sector":"Information Technology","industry":"Electronic Equipment & Instruments","market_cap":null,"exchange":"NYSE/NASDAQ","close":612.91,"prev_close":616.65,"change_pct":-0.6065,"rsi_14":null,"sma_50":null,"sma_200":null,"bb_pctb":null,"above_sma50":null,"above_sma200":null},{"ticker":"MLM","name":"Martin Marietta Materials","sector":"Materials","industry":"Construction Materials","market_cap":null,"exchange":"NYSE/NASDAQ","close":604.18,"prev_close":609.88,"change_pct":-0.9346,"rsi_14":null,"sma_50":null,"sma_200":null,"bb_pctb":null,"above_sma50":null,"above_sma200":null},{"ticker":"DE","name":"Deere & Company","sector":"Industrials","industry":"Agricultural & Farm Machinery","market_cap":null,"exchange":"NYSE/NASDAQ","close":591.94,"prev_close":598.59,"change_pct":-1.1109,"rsi_14":null,"sma_50":null,"sma_200":null,"bb_pctb":null,"above_sma50":null,"above_sma200":null},{"ticker":"AMAT","name":"Applied Materials","sector":"Information Technology","industry":"Semiconductor Materials & Equipment","market_cap":null,"exchange":"NYSE/NASDAQ","close":585.88,"prev_close":640.18,"change_pct":-8.482,"rsi_14":null,"sma_50":null,"sma_200":null,"bb_pctb":null,"above_sma50":null,"above_sma200":null},{"ticker":"MSCI","name":"MSCI Inc.","sector":"Financials","industry":"Financial Exchanges & Data","market_cap":null,"exchange":"NYSE/NASDAQ","close":581.51,"prev_close":580.85,"change_pct":0.1136,"rsi_14":null,"sma_50":null,"sma_200":null,"bb_pctb":null,"above_sma50":null,"above_sma200":null},{"ticker":"META","name":"Meta Platforms","sector":"Communication Services","industry":"Interactive Media & Services","market_cap":null,"exchange":"NYSE/NASDAQ","close":562.2,"prev_close":563.85,"change_pct":-0.2926,"rsi_14":null,"sma_50":null,"sma_200":null,"bb_pctb":null,"above_sma50":null,"above_sma200":null},{"ticker":"IDXX","name":"Idexx Laboratories","sector":"Health Care","industry":"Health Care Equipment","market_cap":null,"exchange":"NYSE/NASDAQ","close":541.31,"prev_close":545.73,"change_pct":-0.8099,"rsi_14":null,"sma_50":null,"sma_200":null,"bb_pctb":null,"above_sma50":null,"above_sma200":null},{"ticker":"LII","name":"Lennox International","sector":"Industrials","industry":"Building Products","market_cap":null,"exchange":"NYSE/NASDAQ","close":523.59,"prev_close":536.04,"change_pct":-2.3226,"rsi_14":null,"sma_50":null,"sma_200":null,"bb_pctb":null,"above_sma50":null,"above_sma200":null},{"ticker":"AMD","name":"Advanced Micro Devices","sector":"Information Technology","industry":"Semiconductors","market_cap":null,"exchange":"NYSE/NASDAQ","close":519.85,"prev_close":551.63,"change_pct":-5.7611,"rsi_14":null,"sma_50":null,"sma_200":null,"bb_pctb":null,"above_sma50":null,"above_sma200":null},{"ticker":"NOC","name":"Northrop Grumman","sector":"Industrials","industry":"Aerospace & Defense","market_cap":null,"exchange":"NYSE/NASDAQ","close":513.22,"prev_close":507.33,"change_pct":1.161,"rsi_14":null,"sma_50":null,"sma_200":null,"bb_pctb":null,"above_sma50":null,"above_sma200":null},{"ticker":"LIN","name":"Linde plc","sector":"Materials","industry":"Industrial Gases","market_cap":null,"exchange":"NYSE/NASDAQ","close":512.26,"prev_close":516.71,"change_pct":-0.8612,"rsi_14":null,"sma_50":null,"sma_200":null,"bb_pctb":null,"above_sma50":null,"above_sma200":null},{"ticker":"HUBB","name":"Hubbell Incorporated","sector":"Industrials","industry":"Industrial Machinery & Supplies & Components","market_cap":null,"exchange":"NYSE/NASDAQ","close":509.96,"prev_close":539.39,"change_pct":-5.4562,"rsi_14":null,"sma_50":null,"sma_200":null,"bb_pctb":null,"above_sma50":null,"above_sma200":null},{"ticker":"LMT","name":"Lockheed Martin","sector":"Industrials","industry":"Aerospace & Defense","market_cap":null,"exchange":"NYSE/NASDAQ","close":503.67,"prev_close":493.6,"change_pct":2.0401,"rsi_14":null,"sma_50":null,"sma_200":null,"bb_pctb":null,"above_sma50":null,"above_sma200":null},{"ticker":"BRK-B","name":"Berkshire Hathaway","sector":"Financials","industry":"Multi-Sector Holdings","market_cap":null,"exchange":"NYSE/NASDAQ","close":492.81,"prev_close":488.69,"change_pct":0.8431,"rsi_14":null,"sma_50":null,"sma_200":null,"bb_pctb":null,"above_sma50":null,"above_sma200":null},{"ticker":"MA","name":"Mastercard","sector":"Financials","industry":"Transaction & Payment Processing Services","market_cap":null,"exchange":"NYSE/NASDAQ","close":488.07,"prev_close":484.09,"change_pct":0.8222,"rsi_14":null,"sma_50":null,"sma_200":null,"bb_pctb":null,"above_sma50":null,"above_sma200":null},{"ticker":"TT","name":"Trane Technologies","sector":"Industrials","industry":"Building Products","market_cap":null,"exchange":"NYSE/NASDAQ","close":474.34,"prev_close":491.59,"change_pct":-3.509,"rsi_14":null,"sma_50":null,"sma_200":null,"bb_pctb":null,"above_sma50":null,"above_sma200":null},{"ticker":"TMO","name":"Thermo Fisher Scientific","sector":"Health Care","industry":"Life Sciences Tools & Services","market_cap":null,"exchange":"NYSE/NASDAQ","close":469.35,"prev_close":464.01,"change_pct":1.1508,"rsi_14":null,"sma_50":null,"sma_200":null,"bb_pctb":null,"above_sma50":null,"above_sma200":null},{"ticker":"VRTX","name":"Vertex Pharmaceuticals","sector":"Health Care","industry":"Biotechnology","market_cap":null,"exchange":"NYSE/NASDAQ","close":468.42,"prev_close":466.79,"change_pct":0.3492,"rsi_14":null,"sma_50":null,"sma_200":null,"bb_pctb":null,"above_sma50":null,"above_sma200":null},{"ticker":"APP","name":"AppLovin","sector":"Information Technology","industry":"Application Software","market_cap":null,"exchange":"NYSE/NASDAQ","close":467.02,"prev_close":469.39,"change_pct":-0.5049,"rsi_14":null,"sma_50":null,"sma_200":null,"bb_pctb":null,"above_sma50":null,"above_sma200":null}]