[{"ticker":"MOH","name":"Molina Healthcare","sector":"Health Care","industry":"Managed Health Care","market_cap":null,"exchange":"NYQ","close":191.97,"prev_close":191.58,"change_pct":0.2036,"rsi_14":null,"sma_50":null,"sma_200":null,"bb_pctb":null,"above_sma50":null,"above_sma200":null},{"ticker":"PAYC","name":"Paycom","sector":"Industrials","industry":"Human Resource & Employment Services","market_cap":null,"exchange":"NYQ","close":134.9,"prev_close":137.6,"change_pct":-1.9622,"rsi_14":null,"sma_50":null,"sma_200":null,"bb_pctb":null,"above_sma50":null,"above_sma200":null},{"ticker":"LW","name":"Lamb Weston","sector":"Consumer Staples","industry":"Packaged Foods & Meats","market_cap":null,"exchange":"NYQ","close":41.54,"prev_close":41.41,"change_pct":0.3139,"rsi_14":null,"sma_50":null,"sma_200":null,"bb_pctb":null,"above_sma50":null,"above_sma200":null}]